dj_auth_audit/__init__.py
dj_auth_audit/admin.py
dj_auth_audit/apps.py
dj_auth_audit/exceptions.py
dj_auth_audit/handlers.py
dj_auth_audit/mixins.py
dj_auth_audit/models.py
dj_auth_audit/serializers.py
dj_auth_audit/signals.py
dj_auth_audit/urls.py
dj_auth_audit/views.py
dj_auth_audit/migrations/0001_initial.py
dj_auth_audit/migrations/__init__.py
dj_auth_audit/static/css/dj_auth_audit.css
dj_auth_audit/static/js/dj_auth_audit.js
dj_auth_audit/templates/dj_auth_audit/base.html
dj_auth_audit/test_utils/__init__.py
dj_auth_audit/test_utils/test_app/__init__.py
dj_auth_audit/test_utils/test_app/admin.py
dj_auth_audit/test_utils/test_app/apps.py
dj_auth_audit/test_utils/test_app/models.py
dj_auth_audit/test_utils/test_app/migrations/__init__.py
django_auth_audit-0.0.dist-info/AUTHORS.rst
django_auth_audit-0.0.dist-info/LICENSE
django_auth_audit-0.0.dist-info/METADATA
django_auth_audit-0.0.dist-info/WHEEL
django_auth_audit-0.0.dist-info/top_level.txt
django_auth_audit-0.0.dist-info/RECORD
