Metadata-Version: 2.1
Name: django-auth-audit
Version: 0.0
Summary: Your project description goes here
Home-page: https://github.com/abdelbaki1/django-auth-audit
Author: Chrigui Abdelbaki
Author-email: chriguiabdelbaki@gmail.com
License: MIT
Keywords: dj-auth-audit
Platform: UNKNOWN
Classifier: Development Status :: 3 - Alpha
Classifier: Intended Audience :: Developers
Classifier: License :: OSI Approved :: BSD License
Classifier: Natural Language :: English
Classifier: Programming Language :: Python :: 2
Classifier: Programming Language :: Python :: 2.7
Classifier: Programming Language :: Python :: 3
Classifier: Programming Language :: Python :: 3.5
Classifier: Programming Language :: Python :: 3.6
Requires-Dist: django-model-utils (>=2.0)
